README
setup.py
TinfoilHat.egg-info/PKG-INFO
TinfoilHat.egg-info/SOURCES.txt
TinfoilHat.egg-info/dependency_links.txt
TinfoilHat.egg-info/requires.txt
TinfoilHat.egg-info/top_level.txt
tinfoilhat/__init__.py