Metadata-Version: 1.0
Name: TinfoilHat
Version: 0.2
Summary: 
Home-page: http://github.com/pneff/tinfoilhat/tree/master
Author: Patrice Neff <software@patrice.ch>
Author-email: UNKNOWN
License: BSD
Download-URL: http://pypi.python.org/pypi/TinfoilHat
Platform: UNKNOWN
Classifier: Development Status :: 3 - Alpha
Classifier: Intended Audience :: Developers
Classifier: License :: OSI Approved :: BSD License
Classifier: Programming Language :: Python :: 2.6
Classifier: Topic :: Internet :: WWW/HTTP
